manifold3d.cpython-312-x86_64-linux-gnu.so
manifold3d.pyi
manifold3d-3.2.0.dist-info/METADATA
manifold3d-3.2.0.dist-info/WHEEL
manifold3d-3.2.0.dist-info/RECORD
manifold3d-3.2.0.dist-info/licenses/AUTHORS
manifold3d-3.2.0.dist-info/licenses/LICENSE
