Metadata-Version: 2.2
Name: manifold3d
Version: 3.2.0
Summary: Library for geometric robustness
Author-Email: Emmett Lalish <elalish@gmail.com>
Classifier: Development Status :: 5 - Production/Stable
Classifier: License :: OSI Approved :: Apache Software License
Classifier: Operating System :: OS Independent
Classifier: Programming Language :: C++
Classifier: Topic :: Multimedia :: Graphics :: 3D Modeling
Project-URL: Homepage, https://github.com/elalish/manifold
Project-URL: Bug Tracker, https://github.com/elalish/manifold/issues
Requires-Python: >=3.8
Requires-Dist: numpy; python_version < "3.12"
Requires-Dist: numpy>=1.26.0b1; python_version >= "3.12"
